 [{
  "name": "Potato",
  "cost": 40
  }, {
  "name": "Cheese",
  "cost": 10
  }, {
  "name": "Salmon",
  "cost": 100
  }, {
  "name": "Chicken",
  "cost": 340
  }, {
  "name": "Milk",
  "cost": 20
  }, {
  "name": "Ice-Cream",
  "cost": 300
  }, {
  "name": "Eggs",
  "cost": 4
  }, {
  "name": "Fish",
  "cost": 40
  }, {
  "name": "Beef",
  "cost": 500
  }, {
  "name": "Bacon",
  "cost": 30
  }, {
  "name": "Pizza",
  "cost": 100
  }, {
  "name": "Bread",
  "cost": 600
  }, {
  "name": "Water",
  "cost": 50
  }, {
  "name": "Sandwich",
  "cost": 765
  }, {
  "name": "Pasta",
  "cost": 700
  }, {
  "name": "Rice",
  "cost": 95
  }, {
  "name": "corn",
  "cost": 100
  }, {
  "name": "Celery",
  "cost": 570
  }, {
  "name": "Pickles",
  "cost": 900
  }, {
  "name": "Chocolate chips",
  "cost": 90
  }, {
  "name": "Oatmeal",
  "cost": 1
  }, {
  "name": "Popcorn",
  "cost": 456.23
  }, {
  "name": "Juice concentrated/ Juice Unconcentrated",
  "cost": 1000.11
  }, {
  "name": " Black pepper",
  "cost": 0.345
  }]
